setup.py
conjurer/__init__.py
conjurer/expressions.py
conjurer/mapper.py
conjurer/transforms.py
python_conjurer.egg-info/PKG-INFO
python_conjurer.egg-info/SOURCES.txt
python_conjurer.egg-info/dependency_links.txt
python_conjurer.egg-info/top_level.txt