Metadata-Version: 1.1
Name: python-conjurer
Version: 0.1
Summary: Simple mapping between SQLAlchemy results and objects
Home-page: UNKNOWN
Author: Martin Atkins
Author-email: mart@degeneration.co.uk
License: UNKNOWN
Platform: UNKNOWN
Requires: sqlalchemy
Provides: conjurer
